iutest/__init__.py
iutest/_version.py
iutest/cli.py
iutest/dependencies.py
iutest/qt.py
iutest/core/__init__.py
iutest/core/appsettings.py
iutest/core/constants.py
iutest/core/gotocode.py
iutest/core/iconutils.py
iutest/core/importutils.py
iutest/core/loggingutils.py
iutest/core/pathutils.py
iutest/core/pyunitutils.py
iutest/core/runinfo.py
iutest/core/testmanager.py
iutest/core/uistream.py
iutest/core/runners/__init__.py
iutest/core/runners/base.py
iutest/core/runners/nose2runner.py
iutest/core/runners/pytestrunner.py
iutest/core/runners/pyunitrunner.py
iutest/core/runners/registry.py
iutest/core/runners/runnerconstants.py
iutest/dcc/__init__.py
iutest/dcc/dccmaya.py
iutest/dcc/standalone.py
iutest/docs/developer.md
iutest/docs/images/iutest-0.1.5.gif
iutest/icons/all.svg
iutest/icons/all_error.svg
iutest/icons/all_expectedFailure.svg
iutest/icons/all_failed.svg
iutest/icons/all_running.svg
iutest/icons/all_skipped.svg
iutest/icons/all_success.svg
iutest/icons/all_unepectedSuccess.svg
iutest/icons/autoFilter.svg
iutest/icons/caseSensitive.svg
iutest/icons/clear.svg
iutest/icons/clearLog.svg
iutest/icons/clearLogOnRun.svg
iutest/icons/config.svg
iutest/icons/iutest.svg
iutest/icons/module.svg
iutest/icons/module_error.svg
iutest/icons/module_expectedFailure.svg
iutest/icons/module_failed.svg
iutest/icons/module_running.svg
iutest/icons/module_skipped.svg
iutest/icons/module_success.svg
iutest/icons/module_unepectedSuccess.svg
iutest/icons/more.svg
iutest/icons/nose2.svg
iutest/icons/package.svg
iutest/icons/package_error.svg
iutest/icons/package_expectedFailure.svg
iutest/icons/package_failed.svg
iutest/icons/package_running.svg
iutest/icons/package_skipped.svg
iutest/icons/package_success.svg
iutest/icons/package_unepectedSuccess.svg
iutest/icons/panelMode_both.svg
iutest/icons/panelMode_left.svg
iutest/icons/panelMode_right.svg
iutest/icons/pytest.svg
iutest/icons/pyunit.svg
iutest/icons/reimport.svg
iutest/icons/reimportAndRerun.svg
iutest/icons/reloadUI.svg
iutest-0.1.5.dist-info/LICENSE
iutest-0.1.5.dist-info/METADATA
iutest-0.1.5.dist-info/WHEEL
iutest-0.1.5.dist-info/entry_points.txt
iutest-0.1.5.dist-info/top_level.txt
iutest-0.1.5.dist-info/RECORD
