Metadata-Version: 2.1
Name: iutest
Version: 0.1.5
Summary: An interactive python test runner supports various test frameworks.
Home-page: https://github.com/mgland/iutest
Author: Miguel Gao
Author-email: opensourcemg@gmail.com
License: MIT
Platform: UNKNOWN
Classifier: License :: OSI Approved :: MIT License
Classifier: Programming Language :: Python :: 2.7
Classifier: Programming Language :: Python :: 3
Classifier: Programming Language :: Python :: 3.7
Classifier: Framework :: Pytest
Classifier: Topic :: Software Development
Classifier: Topic :: Software Development :: Testing
Classifier: Topic :: Software Development :: Testing :: Unit
Classifier: Intended Audience :: Developers
